{
  "version": 6,
  "cmakeMinimumRequired": {
    "major": 3,
    "minor": 22,
    "patch": 0
  },
  "configurePresets": [
    {
      "name": "debug",
      "displayName": "Debug",
      "description": "Debug build in out/build/debug",
      "generator": "Ninja Multi-Config",
      "binaryDir": "${sourceDir}/out/build/debug"
    },
    {
      "name": "release",
      "displayName": "Release",
      "description": "Release build in out/build/release",
      "generator": "Ninja Multi-Config",
      "binaryDir": "${sourceDir}/out/build/release"
    }
  ],
  "buildPresets": [
    {
      "name": "debug",
      "displayName": "Build Debug",
      "configurePreset": "debug",
      "configuration": "Debug"
    },
    {
      "name": "release",
      "displayName": "Build Release",
      "configurePreset": "release",
      "configuration": "Release"
    }
  ]
}
